[
    { "clue": "Nama pertama dalam Alkitab yang berarti 'Tanah Kering'", "word": "Adam" },
    { "clue": "Siapakah yang memimpin bangsa Israel keluar dari perbudakan Mesir?", "word": "Musa" },
    { "clue": "Nama tokoh yang memimpin Israel dalam penaklukan Yerikho", "word": "Yosua" },
    { "clue": "Buku pertama dalam Alkitab yang berisi tentang penciptaan dunia", "word": "Kejadian" },
    { "clue": "Siapakah yang menulis sebagian besar surat-surat dalam Perjanjian Baru?", "word": "RasulPaulus" },
    { "clue": "Apa yang disebut sebagai 'Bapa Doa' oleh Yesus dalam Kitab Suci?", "word": "DoaBapaKami" },
    { "clue": "Nama kitab yang berisi kisah pengorbanan Nabi Yunus di dalam perut ikan paus", "word": "KitabYunus" },
    { "clue": "Apakah yang dihasilkan oleh Gideon saat ia mengalahkan orang Midian?", "word": "Terompet" },
    { "clue": "Nama tempat kelahiran Yesus menurut Alkitab", "word": "Betlehem" },
    { "clue": "Siapa yang menjadi ratu dan mendengar hikayat Nabi Salomo?", "word": "RatuSabi" },
    { "clue": "Kitab Perjanjian Baru yang berisi catatan hidup dan ajaran Yesus", "word": "Injil" },
    { "clue": "Nama putra yang dipersembahkan oleh Abraham sebagai tanda iman dan taat kepada Allah", "word": "Ishak" },
    { "clue": "Siapa yang memimpin orang Israel melintasi Laut Merah dalam perjalanan keluar dari Mesir?", "word": "Musa" },
    { "clue": "Nama kitab yang berisi tentang kisah cinta antara Raja Salomo dan Ratu Seba", "word": "KidungAgung" },
    { "clue": "Nama tempat di mana Yesus mengucapkan Khotbah di Bukit", "word": "BukitZaitun" }
]